inferra/__init__.py
inferra/api_export.py
inferra/version.py
inferra/layers/__init__.py
inferra/layers/tensorflow_layers/__init__.py
inferra/layers/tensorflow_layers/layer.py
inferra/layers/torch_layers/ResidualBlock.py
inferra/layers/torch_layers/SqueezeExcitation.py
inferra/layers/torch_layers/Swish.py
inferra/layers/torch_layers/__init__.py
inferra/layers/torch_layers/layer.py
inferra/layers/torch_layers/test_torch_layers.py
inferra/models/__init__.py
inferra/models/au57.py
inferra/models/tensorflow_model.py
inferra/models/torch_model.py
inferra/src/__init__.py
inferra/src/api_export.py
inferra/src/version.py
inferra/src/layers/__init__.py
inferra/src/layers/tensorflow_layers/__init__.py
inferra/src/layers/tensorflow_layers/layer.py
inferra/src/layers/torch_layers/ResidualBlock.py
inferra/src/layers/torch_layers/SqueezeExcitation.py
inferra/src/layers/torch_layers/Swish.py
inferra/src/layers/torch_layers/__init__.py
inferra/src/layers/torch_layers/layer.py
inferra/src/layers/torch_layers/test_torch_layers.py
inferra/src/models/__init__.py
inferra/src/models/au57.py
inferra/src/models/tensorflow_model.py
inferra/src/models/torch_model.py
inferra/src/utils/inferra_utils.py
inferra/utils/inferra_utils.py
inferra-1.2.dist-info/METADATA
inferra-1.2.dist-info/WHEEL
inferra-1.2.dist-info/top_level.txt
inferra-1.2.dist-info/RECORD
