Metadata-Version: 2.4
Name: inferra
Version: 1.2
Summary: Inferra is an open-source platform to host, explore, and run pre-trained ML, DL, and NLP models with an interactive UI.
Author-email: Mohamed Ashraf <ma2736666@gmail.com>
License-Expression: Apache-2.0
Project-URL: Home, https://github.com/your-org/inferra
Project-URL: Repository, https://github.com/your-org/inferra
Classifier: Development Status :: 3 - Alpha
Classifier: Programming Language :: Python :: 3
Classifier: Programming Language :: Python :: 3.9
Classifier: Programming Language :: Python :: 3.10
Classifier: Programming Language :: Python :: 3.11
Classifier: Programming Language :: Python :: 3 :: Only
Classifier: Operating System :: Unix
Classifier: Operating System :: Microsoft :: Windows
Classifier: Operating System :: MacOS
Classifier: Intended Audience :: Science/Research
Classifier: Topic :: Scientific/Engineering
Classifier: Topic :: Software Development
Requires-Python: >=3.9
Requires-Dist: keras>=3.10
Requires-Dist: absl-py
Requires-Dist: numpy
Requires-Dist: packaging
Requires-Dist: regex
Requires-Dist: rich
Requires-Dist: kagglehub
Requires-Dist: tensorflow-text; platform_system != "Windows"
